Metadata-Version: 2.1
Name: parcoursupy
Version: 1.0.0
Summary: Python API wrapper pour Parcoursup
Home-page: https://www.github.com/Bapt5/parcoursupy
Download-URL: https://github.com/Bapt5/parcoursupy/archive/refs/tags/v1.0.0.tar.gz
Author: Bapt5
Author-email: drouillet.baptiste@gmail.com
License: MPL2.0
Keywords: parcoursup,wrapper-api,api
Requires-Python: >=3.7
License-File: LICENSE
